xendit/__init__.py
xendit/api_client.py
xendit/apis/__init__.py
xendit/balance_and_transaction/__init__.py
xendit/balance_and_transaction/balance_api.py
xendit/balance_and_transaction/model/__init__.py
xendit/balance_and_transaction/model/balance.py
xendit/balance_and_transaction/model/channels_categories.py
xendit/balance_and_transaction/model/currency.py
xendit/balance_and_transaction/model/date_range_filter.py
xendit/balance_and_transaction/model/fee_response.py
xendit/balance_and_transaction/model/link_item.py
xendit/balance_and_transaction/model/server_error.py
xendit/balance_and_transaction/model/transaction_id.py
xendit/balance_and_transaction/model/transaction_response.py
xendit/balance_and_transaction/model/transaction_response_type.py
xendit/balance_and_transaction/model/transaction_statuses.py
xendit/balance_and_transaction/model/transaction_types.py
xendit/balance_and_transaction/model/transactions_response.py
xendit/balance_and_transaction/model/validation_error.py
xendit/balance_and_transaction/transaction_api.py
xendit/configuration.py
xendit/customer/__init__.py
xendit/customer/customer_api.py
xendit/customer/model/__init__.py
xendit/customer/model/account_bank.py
xendit/customer/model/account_card.py
xendit/customer/model/account_ewallet.py
xendit/customer/model/account_otc.py
xendit/customer/model/account_pay_later.py
xendit/customer/model/account_qr_code.py
xendit/customer/model/address.py
xendit/customer/model/address_request.py
xendit/customer/model/address_status.py
xendit/customer/model/business_detail.py
xendit/customer/model/country_code.py
xendit/customer/model/create_customer400_response.py
xendit/customer/model/create_customer400_response_all_of.py
xendit/customer/model/customer.py
xendit/customer/model/customer_request.py
xendit/customer/model/employment_detail.py
xendit/customer/model/end_customer_status.py
xendit/customer/model/error.py
xendit/customer/model/get_customer_by_reference_id200_response.py
xendit_python-6.4.0.dist-info/LICENSE
xendit_python-6.4.0.dist-info/METADATA
xendit_python-6.4.0.dist-info/WHEEL
xendit_python-6.4.0.dist-info/RECORD
