Metadata-Version: 2.1
Name: xendit-python
Version: 6.4.0
Summary: Xendit REST API Client for Python - Invoice, Payment Request, Payment Method, Refund, Balance, Transaction, Customer, and Payout Services https://xendit.github.io/apireference/
Home-page: https://github.com/xendit/xendit-python
License: MIT
Keywords: xendit,sdk
Author: DevX Team
Author-email: devx@xendit.co
Requires-Python: >=3.10,<4.0
Classifier: Intended Audience :: Developers
Classifier: License :: OSI Approved :: MIT License
Classifier: Operating System :: OS Independent
Classifier: Programming Language :: Python :: 3
Classifier: Programming Language :: Python :: 3.10
Classifier: Programming Language :: Python :: 3.11
Requires-Dist: requests (>=2.23.0,<3.0.0)
Project-URL: Repository, https://github.com/xendit/xendit-python
